Metadata-Version: 2.1
Name: odoo14-addon-report_fillpdf
Version: 14.0.1.0.2.dev6
Summary: Base module that fills PDFs
Home-page: https://github.com/OCA/reporting-engine
Author: Creu Blanca,Odoo Community Association (OCA)
Author-email: support@odoo-community.org
License: AGPL-3
Classifier: Programming Language :: Python
Classifier: Framework :: Odoo
Classifier: Framework :: Odoo :: 14.0
Classifier: License :: OSI Approved :: GNU Affero General Public License v3
Requires-Python: >=3.6
Requires-Dist: fdfgen
Requires-Dist: odoo<14.1dev,>=14.0a
